README.rst
setup.py
cullerton/__init__.py
cullerton.agora.egg-info/PKG-INFO
cullerton.agora.egg-info/SOURCES.txt
cullerton.agora.egg-info/dependency_links.txt
cullerton.agora.egg-info/entry_points.txt
cullerton.agora.egg-info/namespace_packages.txt
cullerton.agora.egg-info/requires.txt
cullerton.agora.egg-info/top_level.txt
cullerton/agora/__init__.py
cullerton/agora/agora.py
cullerton/agora/exceptions.py
cullerton/agora/initialize_db.py
cullerton/agora/logging.py
cullerton/agora/models.py
cullerton/agora/session.py
cullerton/agora/tests.py