Metadata-Version: 1.1
Name: cullerton.agora
Version: 0.0.2
Summary: A forum for ideas
Home-page: https://github.com/cullerton/cullerton.agora
Author: mike cullerton
Author-email: michaelc@cullerton.com
License: UNKNOWN
Download-URL: https://github.com/cullerton/cullerton.agora/tarball/0.0.2
Keywords: academic,simple,example
Platform: UNKNOWN
